{
    "files": [
        {
            "name": "StepManiaX",
            "type": "folder",
            "children": [
                {
                    "name": "Ari Oh (Factory Team Eurobeat Mix) - Jenny Kee.mp3",
                    "type": "file",
                    "size": "1.49 MB",
                    "url": "https://host.qtdt.dpdns.org/StepManiaX/Ari Oh (Factory Team Eurobeat Mix) - Jenny Kee.mp3"
                },
                {
                    "name": "Beethoven Virus (2021 Yahpp Remix) - BanYa.mp3",
                    "type": "file",
                    "size": "1.59 MB",
                    "url": "https://host.qtdt.dpdns.org/StepManiaX/Beethoven Virus (2021 Yahpp Remix) - BanYa.mp3"
                }
            ]
        },
        {
            "name": "GitHub.url",
            "type": "file",
            "size": "1 B",
            "url": "https://github.com/haoqi75/haoqi-gweb"
        }
    ]
}